littlelearn/__init__.py
littlelearn/DeepLearning/__init__.py
littlelearn/DeepLearning/Loss/Loss.py
littlelearn/DeepLearning/Loss/__init__.py
littlelearn/DeepLearning/Model/Model.py
littlelearn/DeepLearning/Model/__init__.py
littlelearn/DeepLearning/activations/Activations.py
littlelearn/DeepLearning/activations/__init__.py
littlelearn/DeepLearning/layers/__init__.py
littlelearn/DeepLearning/layers/temp_layers.py
littlelearn/DeepLearning/optimizers/__init__.py
littlelearn/DeepLearning/optimizers/temp_optimizer.py
littlelearn/GradientReflector/GradientReflector.py
littlelearn/GradientReflector/__init__.py
littlelearn/preprocessing/__init__.py
littlelearn/preprocessing/preprocessing.py
littlelearn/tensor/__init__.py
littlelearn/tensor/tensor.py
littlelearn-1.1.3.dist-info/licenses/LICENSE
littlelearn-1.1.3.dist-info/METADATA
littlelearn-1.1.3.dist-info/WHEEL
littlelearn-1.1.3.dist-info/top_level.txt
littlelearn-1.1.3.dist-info/RECORD
