Metadata-Version: 2.4
Name: littlelearn
Version: 1.1.3
Summary: Deep learning API
Home-page: https://github.com/Airinchan818/LittleLearn
Author: Candra Alpin Gunawan
Author-email: hinamatsuriairin@gmail.com
Keywords: deep learning,artificial intellengence,engine grad,ai,framework,api,machine learning
Classifier: Development Status :: 5 - Production/Stable
Classifier: Programming Language :: Python :: 3
Classifier: License :: OSI Approved :: Apache Software License
Classifier: Intended Audience :: Developers
Classifier: Topic :: Scientific/Engineering :: Artificial Intelligence
Requires-Python: >=3.7
License-File: LICENSE
Requires-Dist: jax
Requires-Dist: numpy
Requires-Dist: tqdm
Requires-Dist: pandas
Requires-Dist: matplotlib
Dynamic: author
Dynamic: author-email
Dynamic: classifier
Dynamic: description
Dynamic: description-content-type
Dynamic: home-page
Dynamic: keywords
Dynamic: license-file
Dynamic: requires-dist
Dynamic: requires-python
Dynamic: summary
